IPFMC/__init__.py
IPFMC/analysis.py
IPFMC/direct.py
IPFMC/separate.py
IPFMC-1.1.1.dist-info/LICENSE.txt
IPFMC-1.1.1.dist-info/METADATA
IPFMC-1.1.1.dist-info/WHEEL
IPFMC-1.1.1.dist-info/top_level.txt
IPFMC-1.1.1.dist-info/RECORD
