Metadata-Version: 2.1
Name: IPFMC
Version: 1.1.1
Summary: A tool for interpretable multi-omics integrated clustering.
Home-page: https://github.com/BioLemon/IPFMC
Author: Haoyang Zhang
Author-email: 2609668279@qq.com
License: MIT
Platform: UNKNOWN
Classifier: License :: OSI Approved :: MIT License
Classifier: Programming Language :: Python
Classifier: Programming Language :: Python :: 3
Classifier: Programming Language :: Python :: 3.6
Classifier: Programming Language :: Python :: Implementation :: CPython
Classifier: Programming Language :: Python :: Implementation :: PyPy
Requires-Python: >=3.6.0
License-File: LICENSE.txt
Requires-Dist: numpy
Requires-Dist: pandas
Requires-Dist: scikit-learn
Requires-Dist: scipy
Requires-Dist: snfpy
